[
  {
    "amount": 1.0, 
    "start_at": -680, 
    "description": "TempBasal: 1.5U/hour over 30min", 
    "type": "TempBasal", 
    "unit": "U/hour", 
    "end_at": -650
  }, 
  {
    "amount": 1.0, 
    "start_at": -720, 
    "description": "TempBasal: 1.5U/hour over 11min", 
    "type": "TempBasal", 
    "unit": "U/hour", 
    "end_at": -709
  }, 
  {
    "amount": 1.0, 
    "start_at": -735, 
    "description": "TempBasal: 1.5U/hour over 9min", 
    "type": "TempBasal", 
    "unit": "U/hour", 
    "end_at": -726
  }, 
  {
    "amount": 1.0, 
    "start_at": -825, 
    "description": "TempBasal: 1.5U/hour over 30min", 
    "type": "TempBasal", 
    "unit": "U/hour", 
    "end_at": -795
  }, 
  {
    "amount": 1.0, 
    "start_at": -850, 
    "description": "TempBasal: 1.5U/hour over 9min", 
    "type": "TempBasal", 
    "unit": "U/hour", 
    "end_at": -841
  }, 
  {
    "amount": 0.8500000000000001, 
    "start_at": -860, 
    "description": "TempBasal: 1.35U/hour over 10min", 
    "type": "TempBasal", 
    "unit": "U/hour", 
    "end_at": -850
  }, 
  {
    "amount": -0.375, 
    "start_at": -910, 
    "description": "TempBasal: 0.125U/hour over 15min", 
    "type": "TempBasal", 
    "unit": "U/hour", 
    "end_at": -895
  }, 
  {
    "amount": 1.0, 
    "start_at": -934, 
    "description": "TempBasal: 1.5U/hour over 4min", 
    "type": "TempBasal", 
    "unit": "U/hour", 
    "end_at": -930
  }, 
  {
    "amount": 0.925, 
    "start_at": -975, 
    "description": "TempBasal: 1.425U/hour over 30min", 
    "type": "TempBasal", 
    "unit": "U/hour", 
    "end_at": -945
  }, 
  {
    "amount": -0.5, 
    "start_at": -990, 
    "description": "TempBasal: 0.0U/hour over 9min", 
    "type": "TempBasal", 
    "unit": "U/hour", 
    "end_at": -981
  }, 
  {
    "amount": -0.5, 
    "start_at": -1000, 
    "description": "TempBasal: 0.0U/hour over 10min", 
    "type": "TempBasal", 
    "unit": "U/hour", 
    "end_at": -990
  }, 
  {
    "amount": -0.5, 
    "start_at": -1005, 
    "description": "TempBasal: 0.0U/hour over 4min", 
    "type": "TempBasal", 
    "unit": "U/hour", 
    "end_at": -1001
  }, 
  {
    "amount": -0.5, 
    "start_at": -1010, 
    "description": "TempBasal: 0.0U/hour over 5min", 
    "type": "TempBasal", 
    "unit": "U/hour", 
    "end_at": -1005
  }, 
  {
    "amount": 0.875, 
    "start_at": -1055, 
    "description": "TempBasal: 1.375U/hour over 9min", 
    "type": "TempBasal", 
    "unit": "U/hour", 
    "end_at": -1046
  }, 
  {
    "amount": 0.4, 
    "start_at": -1060, 
    "description": "TempBasal: 0.9U/hour over 4min", 
    "type": "TempBasal", 
    "unit": "U/hour", 
    "end_at": -1056
  }, 
  {
    "amount": 0.8500000000000001, 
    "start_at": -2495, 
    "description": "TempBasal: 1.35U/hour over 5min", 
    "type": "TempBasal", 
    "unit": "U/hour", 
    "end_at": -2490
  }, 
  {
    "amount": 0.75, 
    "start_at": -2514, 
    "description": "TempBasal: 1.25U/hour over 10min", 
    "type": "TempBasal", 
    "unit": "U/hour", 
    "end_at": -2504
  }, 
  {
    "amount": 0.6000000000000001, 
    "start_at": -2525, 
    "description": "TempBasal: 1.1U/hour over 5min", 
    "type": "TempBasal", 
    "unit": "U/hour", 
    "end_at": -2520
  }, 
  {
    "amount": 0.6000000000000001, 
    "start_at": -2595, 
    "description": "TempBasal: 1.1U/hour over 24min", 
    "type": "TempBasal", 
    "unit": "U/hour", 
    "end_at": -2571
  }, 
  {
    "amount": 0.4, 
    "start_at": -2599, 
    "description": "TempBasal: 0.9U/hour over 4min", 
    "type": "TempBasal", 
    "unit": "U/hour", 
    "end_at": -2595
  }, 
  {
    "amount": -0.3, 
    "start_at": -2615, 
    "description": "TempBasal: 0.2U/hour over 5min", 
    "type": "TempBasal", 
    "unit": "U/hour", 
    "end_at": -2610
  }, 
  {
    "amount": 1.0, 
    "start_at": -2679, 
    "description": "TempBasal: 1.5U/hour over 5min", 
    "type": "TempBasal", 
    "unit": "U/hour", 
    "end_at": -2674
  }, 
  {
    "amount": 1.0, 
    "start_at": -2710, 
    "description": "TempBasal: 1.5U/hour over 30min", 
    "type": "TempBasal", 
    "unit": "U/hour", 
    "end_at": -2680
  }, 
  {
    "amount": 0.675, 
    "start_at": -2715, 
    "description": "TempBasal: 1.175U/hour over 4min", 
    "type": "TempBasal", 
    "unit": "U/hour", 
    "end_at": -2711
  }, 
  {
    "amount": -0.5, 
    "start_at": -2735, 
    "description": "TempBasal: 0.0U/hour over 14min", 
    "type": "TempBasal", 
    "unit": "U/hour", 
    "end_at": -2721
  }, 
  {
    "amount": -0.5, 
    "start_at": -2740, 
    "description": "TempBasal: 0.0U/hour over 5min", 
    "type": "TempBasal", 
    "unit": "U/hour", 
    "end_at": -2735
  }, 
  {
    "amount": -0.5, 
    "start_at": -2745, 
    "description": "TempBasal: 0.0U/hour over 5min", 
    "type": "TempBasal", 
    "unit": "U/hour", 
    "end_at": -2740
  }, 
  {
    "amount": -0.5, 
    "start_at": -2749, 
    "description": "TempBasal: 0.0U/hour over 4min", 
    "type": "TempBasal", 
    "unit": "U/hour", 
    "end_at": -2745
  }, 
  {
    "amount": -0.5, 
    "start_at": -2754, 
    "description": "TempBasal: 0.0U/hour over 5min", 
    "type": "TempBasal", 
    "unit": "U/hour", 
    "end_at": -2749
  }, 
  {
    "amount": -0.4, 
    "start_at": -2759, 
    "description": "TempBasal: 0.1U/hour over 5min", 
    "type": "TempBasal", 
    "unit": "U/hour", 
    "end_at": -2754
  }, 
  {
    "amount": -0.45, 
    "start_at": -2805, 
    "description": "TempBasal: 0.05U/hour over 10min", 
    "type": "TempBasal", 
    "unit": "U/hour", 
    "end_at": -2795
  }, 
  {
    "amount": -0.3, 
    "start_at": -2810, 
    "description": "TempBasal: 0.2U/hour over 4min", 
    "type": "TempBasal", 
    "unit": "U/hour", 
    "end_at": -2806
  }, 
  {
    "amount": 0.5, 
    "start_at": -2824, 
    "description": "TempBasal: 1.0U/hour over 9min", 
    "type": "TempBasal", 
    "unit": "U/hour", 
    "end_at": -2815
  }, 
  {
    "amount": 0.30000000000000004, 
    "start_at": -2829, 
    "description": "TempBasal: 0.8U/hour over 5min", 
    "type": "TempBasal", 
    "unit": "U/hour", 
    "end_at": -2824
  }, 
  {
    "amount": 0.8, 
    "start_at": -2850, 
    "description": "TempBasal: 1.3U/hour over 9min", 
    "type": "TempBasal", 
    "unit": "U/hour", 
    "end_at": -2841
  }, 
  {
    "amount": 0.35, 
    "start_at": -2855, 
    "description": "TempBasal: 0.85U/hour over 5min", 
    "type": "TempBasal", 
    "unit": "U/hour", 
    "end_at": -2850
  }, 
  {
    "amount": 0.675, 
    "start_at": -2915, 
    "description": "TempBasal: 1.175U/hour over 9min", 
    "type": "TempBasal", 
    "unit": "U/hour", 
    "end_at": -2906
  }, 
  {
    "amount": 0.42500000000000004, 
    "start_at": -2920, 
    "description": "TempBasal: 0.925U/hour over 5min", 
    "type": "TempBasal", 
    "unit": "U/hour", 
    "end_at": -2915
  }, 
  {
    "amount": 0.35, 
    "start_at": -2930, 
    "description": "TempBasal: 0.85U/hour over 9min", 
    "type": "TempBasal", 
    "unit": "U/hour", 
    "end_at": -2921
  }
]