[
  {
    "amount": 1.0, 
    "start_at": -69, 
    "description": "TempBasal: 1.5U/hour over 29min", 
    "type": "TempBasal", 
    "unit": "U/hour", 
    "end_at": -40
  }, 
  {
    "amount": 1.0, 
    "start_at": -105, 
    "description": "TempBasal: 1.5U/hour over 30min", 
    "type": "TempBasal", 
    "unit": "U/hour", 
    "end_at": -75
  }, 
  {
    "amount": 0.55, 
    "start_at": -125, 
    "description": "TempBasal: 1.05U/hour over 20min", 
    "type": "TempBasal", 
    "unit": "U/hour", 
    "end_at": -105
  }, 
  {
    "amount": 0.4, 
    "start_at": -130, 
    "description": "TempBasal: 0.9U/hour over 5min", 
    "type": "TempBasal", 
    "unit": "U/hour", 
    "end_at": -125
  }, 
  {
    "amount": -0.3, 
    "start_at": -135, 
    "description": "TempBasal: 0.2U/hour over 5min", 
    "type": "TempBasal", 
    "unit": "U/hour", 
    "end_at": -130
  }, 
  {
    "amount": -0.25, 
    "start_at": -150, 
    "description": "TempBasal: 0.25U/hour over 4min", 
    "type": "TempBasal", 
    "unit": "U/hour", 
    "end_at": -146
  }, 
  {
    "amount": 1.0, 
    "start_at": -180, 
    "description": "TempBasal: 1.5U/hour over 25min", 
    "type": "TempBasal", 
    "unit": "U/hour", 
    "end_at": -155
  }, 
  {
    "amount": 1.0, 
    "start_at": -215, 
    "description": "TempBasal: 1.5U/hour over 30min", 
    "type": "TempBasal", 
    "unit": "U/hour", 
    "end_at": -185
  }, 
  {
    "amount": 0.55, 
    "start_at": -225, 
    "description": "TempBasal: 1.05U/hour over 10min", 
    "type": "TempBasal", 
    "unit": "U/hour", 
    "end_at": -215
  }, 
  {
    "amount": 1.0, 
    "start_at": -270, 
    "description": "TempBasal: 1.5U/hour over 14min", 
    "type": "TempBasal", 
    "unit": "U/hour", 
    "end_at": -256
  }, 
  {
    "amount": 0.5, 
    "start_at": -280, 
    "description": "TempBasal: 1.0U/hour over 10min", 
    "type": "TempBasal", 
    "unit": "U/hour", 
    "end_at": -270
  }, 
  {
    "amount": -0.5, 
    "start_at": -300, 
    "description": "TempBasal: 0.0U/hour over 15min", 
    "type": "TempBasal", 
    "unit": "U/hour", 
    "end_at": -285
  }, 
  {
    "amount": -0.5, 
    "start_at": -330, 
    "description": "TempBasal: 0.0U/hour over 29min", 
    "type": "TempBasal", 
    "unit": "U/hour", 
    "end_at": -301
  }, 
  {
    "amount": -0.5, 
    "start_at": -334, 
    "description": "TempBasal: 0.0U/hour over 4min", 
    "type": "TempBasal", 
    "unit": "U/hour", 
    "end_at": -330
  }, 
  {
    "amount": -0.4, 
    "start_at": -340, 
    "description": "TempBasal: 0.1U/hour over 5min", 
    "type": "TempBasal", 
    "unit": "U/hour", 
    "end_at": -335
  }, 
  {
    "amount": 1.0, 
    "start_at": -395, 
    "description": "TempBasal: 1.5U/hour over 25min", 
    "type": "TempBasal", 
    "unit": "U/hour", 
    "end_at": -370
  }, 
  {
    "amount": 0.6000000000000001, 
    "start_at": -400, 
    "description": "TempBasal: 1.1U/hour over 5min", 
    "type": "TempBasal", 
    "unit": "U/hour", 
    "end_at": -395
  }, 
  {
    "amount": -0.3, 
    "start_at": -430, 
    "description": "TempBasal: 0.2U/hour over 25min", 
    "type": "TempBasal", 
    "unit": "U/hour", 
    "end_at": -405
  }, 
  {
    "amount": -0.375, 
    "start_at": -475, 
    "description": "TempBasal: 0.125U/hour over 10min", 
    "type": "TempBasal", 
    "unit": "U/hour", 
    "end_at": -465
  }, 
  {
    "amount": -0.25, 
    "start_at": -480, 
    "description": "TempBasal: 0.25U/hour over 5min", 
    "type": "TempBasal", 
    "unit": "U/hour", 
    "end_at": -475
  }, 
  {
    "amount": 1.0, 
    "start_at": -1155, 
    "description": "TempBasal: 1.5U/hour over 9min", 
    "type": "TempBasal", 
    "unit": "U/hour", 
    "end_at": -1146
  }, 
  {
    "amount": 1.0, 
    "start_at": -1210, 
    "description": "TempBasal: 1.5U/hour over 24min", 
    "type": "TempBasal", 
    "unit": "U/hour", 
    "end_at": -1186
  }, 
  {
    "amount": 1.0, 
    "start_at": -1225, 
    "description": "TempBasal: 1.5U/hour over 10min", 
    "type": "TempBasal", 
    "unit": "U/hour", 
    "end_at": -1215
  }, 
  {
    "amount": 1.0, 
    "start_at": -1260, 
    "description": "TempBasal: 1.5U/hour over 30min", 
    "type": "TempBasal", 
    "unit": "U/hour", 
    "end_at": -1230
  }, 
  {
    "amount": 1.0, 
    "start_at": -1270, 
    "description": "TempBasal: 1.5U/hour over 5min", 
    "type": "TempBasal", 
    "unit": "U/hour", 
    "end_at": -1265
  }, 
  {
    "amount": 1.0, 
    "start_at": -1304, 
    "description": "TempBasal: 1.5U/hour over 30min", 
    "type": "TempBasal", 
    "unit": "U/hour", 
    "end_at": -1274
  }, 
  {
    "amount": 0.925, 
    "start_at": -1340, 
    "description": "TempBasal: 1.425U/hour over 30min", 
    "type": "TempBasal", 
    "unit": "U/hour", 
    "end_at": -1310
  }, 
  {
    "amount": 0.35, 
    "start_at": -1370, 
    "description": "TempBasal: 0.85U/hour over 5min", 
    "type": "TempBasal", 
    "unit": "U/hour", 
    "end_at": -1365
  }, 
  {
    "amount": 1.0, 
    "start_at": -1395, 
    "description": "TempBasal: 1.5U/hour over 20min", 
    "type": "TempBasal", 
    "unit": "U/hour", 
    "end_at": -1375
  }, 
  {
    "amount": 0.42500000000000004, 
    "start_at": -1405, 
    "description": "TempBasal: 0.925U/hour over 9min", 
    "type": "TempBasal", 
    "unit": "U/hour", 
    "end_at": -1396
  }, 
  {
    "amount": -0.5, 
    "start_at": -1415, 
    "description": "TempBasal: 0.0U/hour over 5min", 
    "type": "TempBasal", 
    "unit": "U/hour", 
    "end_at": -1410
  }, 
  {
    "amount": -0.5, 
    "start_at": -1420, 
    "description": "TempBasal: 0.0U/hour over 5min", 
    "type": "TempBasal", 
    "unit": "U/hour", 
    "end_at": -1415
  }, 
  {
    "amount": -0.5, 
    "start_at": -1425, 
    "description": "TempBasal: 0.0U/hour over 4min", 
    "type": "TempBasal", 
    "unit": "U/hour", 
    "end_at": -1421
  }, 
  {
    "amount": -0.5, 
    "start_at": -1430, 
    "description": "TempBasal: 0.0U/hour over 5min", 
    "type": "TempBasal", 
    "unit": "U/hour", 
    "end_at": -1425
  }, 
  {
    "amount": -0.5, 
    "start_at": -1435, 
    "description": "TempBasal: 0.0U/hour over 5min", 
    "type": "TempBasal", 
    "unit": "U/hour", 
    "end_at": -1430
  }, 
  {
    "amount": -0.3, 
    "start_at": -1440, 
    "description": "TempBasal: 0.2U/hour over 4min", 
    "type": "TempBasal", 
    "unit": "U/hour", 
    "end_at": -1436
  }, 
  {
    "amount": 0.925, 
    "start_at": -1470, 
    "description": "TempBasal: 1.425U/hour over 15min", 
    "type": "TempBasal", 
    "unit": "U/hour", 
    "end_at": -1455
  }, 
  {
    "amount": 1.0, 
    "start_at": -1505, 
    "description": "TempBasal: 1.5U/hour over 30min", 
    "type": "TempBasal", 
    "unit": "U/hour", 
    "end_at": -1475
  }, 
  {
    "amount": 0.8, 
    "start_at": -1510, 
    "description": "TempBasal: 1.3U/hour over 5min", 
    "type": "TempBasal", 
    "unit": "U/hour", 
    "end_at": -1505
  }, 
  {
    "amount": -0.5, 
    "start_at": -1524, 
    "description": "TempBasal: 0.0U/hour over 9min", 
    "type": "TempBasal", 
    "unit": "U/hour", 
    "end_at": -1515
  }, 
  {
    "amount": -0.5, 
    "start_at": -1530, 
    "description": "TempBasal: 0.0U/hour over 5min", 
    "type": "TempBasal", 
    "unit": "U/hour", 
    "end_at": -1525
  }
]