[
  {
    "amount": 1.0, 
    "start_at": -5, 
    "description": "TempBasal: 1.5U/hour over 30min", 
    "type": "TempBasal", 
    "unit": "U/hour", 
    "end_at": 25
  }, 
  {
    "amount": 0.875, 
    "start_at": -10, 
    "description": "TempBasal: 1.375U/hour over 5min", 
    "type": "TempBasal", 
    "unit": "U/hour", 
    "end_at": -5
  }, 
  {
    "amount": 1.0, 
    "start_at": -50, 
    "description": "TempBasal: 1.5U/hour over 30min", 
    "type": "TempBasal", 
    "unit": "U/hour", 
    "end_at": -20
  }, 
  {
    "amount": 0.8, 
    "start_at": -60, 
    "description": "TempBasal: 1.3U/hour over 10min", 
    "type": "TempBasal", 
    "unit": "U/hour", 
    "end_at": -50
  }, 
  {
    "amount": 0.675, 
    "start_at": -95, 
    "description": "TempBasal: 1.175U/hour over 10min", 
    "type": "TempBasal", 
    "unit": "U/hour", 
    "end_at": -85
  }, 
  {
    "amount": 1.0, 
    "start_at": -125, 
    "description": "TempBasal: 1.5U/hour over 10min", 
    "type": "TempBasal", 
    "unit": "U/hour", 
    "end_at": -115
  }, 
  {
    "amount": 0.75, 
    "start_at": -135, 
    "description": "TempBasal: 1.25U/hour over 9min", 
    "type": "TempBasal", 
    "unit": "U/hour", 
    "end_at": -126
  }, 
  {
    "amount": 0.35, 
    "start_at": -140, 
    "description": "TempBasal: 0.85U/hour over 5min", 
    "type": "TempBasal", 
    "unit": "U/hour", 
    "end_at": -135
  }, 
  {
    "amount": -0.5, 
    "start_at": -150, 
    "description": "TempBasal: 0.0U/hour over 5min", 
    "type": "TempBasal", 
    "unit": "U/hour", 
    "end_at": -145
  }, 
  {
    "amount": -0.5, 
    "start_at": -155, 
    "description": "TempBasal: 0.0U/hour over 5min", 
    "type": "TempBasal", 
    "unit": "U/hour", 
    "end_at": -150
  }, 
  {
    "amount": -0.5, 
    "start_at": -160, 
    "description": "TempBasal: 0.0U/hour over 5min", 
    "type": "TempBasal", 
    "unit": "U/hour", 
    "end_at": -155
  }, 
  {
    "amount": -0.5, 
    "start_at": -165, 
    "description": "TempBasal: 0.0U/hour over 5min", 
    "type": "TempBasal", 
    "unit": "U/hour", 
    "end_at": -160
  }, 
  {
    "amount": -0.5, 
    "start_at": -175, 
    "description": "TempBasal: 0.0U/hour over 9min", 
    "type": "TempBasal", 
    "unit": "U/hour", 
    "end_at": -166
  }, 
  {
    "amount": -0.5, 
    "start_at": -180, 
    "description": "TempBasal: 0.0U/hour over 5min", 
    "type": "TempBasal", 
    "unit": "U/hour", 
    "end_at": -175
  }, 
  {
    "amount": 1.0, 
    "start_at": -225, 
    "description": "TempBasal: 1.5U/hour over 20min", 
    "type": "TempBasal", 
    "unit": "U/hour", 
    "end_at": -205
  }, 
  {
    "amount": 1.0, 
    "start_at": -260, 
    "description": "TempBasal: 1.5U/hour over 30min", 
    "type": "TempBasal", 
    "unit": "U/hour", 
    "end_at": -230
  }, 
  {
    "amount": 0.42500000000000004, 
    "start_at": -265, 
    "description": "TempBasal: 0.925U/hour over 4min", 
    "type": "TempBasal", 
    "unit": "U/hour", 
    "end_at": -261
  }, 
  {
    "amount": -0.5, 
    "start_at": -280, 
    "description": "TempBasal: 0.0U/hour over 4min", 
    "type": "TempBasal", 
    "unit": "U/hour", 
    "end_at": -276
  }, 
  {
    "amount": -0.5, 
    "start_at": -285, 
    "description": "TempBasal: 0.0U/hour over 5min", 
    "type": "TempBasal", 
    "unit": "U/hour", 
    "end_at": -280
  }, 
  {
    "amount": -0.5, 
    "start_at": -290, 
    "description": "TempBasal: 0.0U/hour over 5min", 
    "type": "TempBasal", 
    "unit": "U/hour", 
    "end_at": -285
  }, 
  {
    "amount": -0.5, 
    "start_at": -295, 
    "description": "TempBasal: 0.0U/hour over 4min", 
    "type": "TempBasal", 
    "unit": "U/hour", 
    "end_at": -291
  }, 
  {
    "amount": -0.375, 
    "start_at": -300, 
    "description": "TempBasal: 0.125U/hour over 5min", 
    "type": "TempBasal", 
    "unit": "U/hour", 
    "end_at": -295
  }, 
  {
    "amount": -0.5, 
    "start_at": -320, 
    "description": "TempBasal: 0.0U/hour over 14min", 
    "type": "TempBasal", 
    "unit": "U/hour", 
    "end_at": -306
  }, 
  {
    "amount": -0.4, 
    "start_at": -325, 
    "description": "TempBasal: 0.1U/hour over 5min", 
    "type": "TempBasal", 
    "unit": "U/hour", 
    "end_at": -320
  }, 
  {
    "amount": 1.0, 
    "start_at": -365, 
    "description": "TempBasal: 1.5U/hour over 20min", 
    "type": "TempBasal", 
    "unit": "U/hour", 
    "end_at": -345
  }, 
  {
    "amount": 0.8, 
    "start_at": -370, 
    "description": "TempBasal: 1.3U/hour over 5min", 
    "type": "TempBasal", 
    "unit": "U/hour", 
    "end_at": -365
  }, 
  {
    "amount": -0.5, 
    "start_at": -390, 
    "description": "TempBasal: 0.0U/hour over 5min", 
    "type": "TempBasal", 
    "unit": "U/hour", 
    "end_at": -385
  }, 
  {
    "amount": -0.5, 
    "start_at": -395, 
    "description": "TempBasal: 0.0U/hour over 5min", 
    "type": "TempBasal", 
    "unit": "U/hour", 
    "end_at": -390
  }, 
  {
    "amount": -0.5, 
    "start_at": -400, 
    "description": "TempBasal: 0.0U/hour over 4min", 
    "type": "TempBasal", 
    "unit": "U/hour", 
    "end_at": -396
  }, 
  {
    "amount": 0.4, 
    "start_at": -450, 
    "description": "TempBasal: 0.9U/hour over 5min", 
    "type": "TempBasal", 
    "unit": "U/hour", 
    "end_at": -445
  }, 
  {
    "amount": 0.4, 
    "start_at": -460, 
    "description": "TempBasal: 0.9U/hour over 5min", 
    "type": "TempBasal", 
    "unit": "U/hour", 
    "end_at": -455
  }, 
  {
    "amount": 1.0, 
    "start_at": -490, 
    "description": "TempBasal: 1.5U/hour over 25min", 
    "type": "TempBasal", 
    "unit": "U/hour", 
    "end_at": -465
  }, 
  {
    "amount": 0.8500000000000001, 
    "start_at": -495, 
    "description": "TempBasal: 1.35U/hour over 5min", 
    "type": "TempBasal", 
    "unit": "U/hour", 
    "end_at": -490
  }, 
  {
    "amount": 0.30000000000000004, 
    "start_at": -500, 
    "description": "TempBasal: 0.8U/hour over 5min", 
    "type": "TempBasal", 
    "unit": "U/hour", 
    "end_at": -495
  }, 
  {
    "amount": -0.4, 
    "start_at": -510, 
    "description": "TempBasal: 0.1U/hour over 4min", 
    "type": "TempBasal", 
    "unit": "U/hour", 
    "end_at": -506
  }, 
  {
    "amount": 0.675, 
    "start_at": -545, 
    "description": "TempBasal: 1.175U/hour over 5min", 
    "type": "TempBasal", 
    "unit": "U/hour", 
    "end_at": -540
  }, 
  {
    "amount": 0.75, 
    "start_at": -555, 
    "description": "TempBasal: 1.25U/hour over 5min", 
    "type": "TempBasal", 
    "unit": "U/hour", 
    "end_at": -550
  }, 
  {
    "amount": 0.42500000000000004, 
    "start_at": -565, 
    "description": "TempBasal: 0.925U/hour over 10min", 
    "type": "TempBasal", 
    "unit": "U/hour", 
    "end_at": -555
  }, 
  {
    "amount": -0.5, 
    "start_at": -580, 
    "description": "TempBasal: 0.0U/hour over 5min", 
    "type": "TempBasal", 
    "unit": "U/hour", 
    "end_at": -575
  }, 
  {
    "amount": -0.5, 
    "start_at": -585, 
    "description": "TempBasal: 0.0U/hour over 5min", 
    "type": "TempBasal", 
    "unit": "U/hour", 
    "end_at": -580
  }, 
  {
    "amount": -0.5, 
    "start_at": -590, 
    "description": "TempBasal: 0.0U/hour over 5min", 
    "type": "TempBasal", 
    "unit": "U/hour", 
    "end_at": -585
  }, 
  {
    "amount": -0.5, 
    "start_at": -595, 
    "description": "TempBasal: 0.0U/hour over 5min", 
    "type": "TempBasal", 
    "unit": "U/hour", 
    "end_at": -590
  }, 
  {
    "amount": 1.0, 
    "start_at": -620, 
    "description": "TempBasal: 1.5U/hour over 5min", 
    "type": "TempBasal", 
    "unit": "U/hour", 
    "end_at": -615
  }
]