[
  {
    "amount": 1.0, 
    "start_at": -164, 
    "description": "TempBasal: 1.5U/hour over 5min", 
    "type": "TempBasal", 
    "unit": "U/hour", 
    "end_at": -159
  }, 
  {
    "amount": 1.0, 
    "start_at": -184, 
    "description": "TempBasal: 1.5U/hour over 10min", 
    "type": "TempBasal", 
    "unit": "U/hour", 
    "end_at": -174
  }, 
  {
    "amount": 0.8500000000000001, 
    "start_at": -1594, 
    "description": "TempBasal: 1.35U/hour over 30min", 
    "type": "TempBasal", 
    "unit": "U/hour", 
    "end_at": -1564
  }, 
  {
    "amount": 0.75, 
    "start_at": -1629, 
    "description": "TempBasal: 1.25U/hour over 30min", 
    "type": "TempBasal", 
    "unit": "U/hour", 
    "end_at": -1599
  }, 
  {
    "amount": 0.6000000000000001, 
    "start_at": -1634, 
    "description": "TempBasal: 1.1U/hour over 5min", 
    "type": "TempBasal", 
    "unit": "U/hour", 
    "end_at": -1629
  }, 
  {
    "amount": 0.42500000000000004, 
    "start_at": -1639, 
    "description": "TempBasal: 0.925U/hour over 5min", 
    "type": "TempBasal", 
    "unit": "U/hour", 
    "end_at": -1634
  }, 
  {
    "amount": 0.8, 
    "start_at": -1674, 
    "description": "TempBasal: 1.3U/hour over 29min", 
    "type": "TempBasal", 
    "unit": "U/hour", 
    "end_at": -1645
  }, 
  {
    "amount": 1.0, 
    "start_at": -1709, 
    "description": "TempBasal: 1.5U/hour over 30min", 
    "type": "TempBasal", 
    "unit": "U/hour", 
    "end_at": -1679
  }, 
  {
    "amount": 0.8500000000000001, 
    "start_at": -1714, 
    "description": "TempBasal: 1.35U/hour over 4min", 
    "type": "TempBasal", 
    "unit": "U/hour", 
    "end_at": -1710
  }, 
  {
    "amount": 0.6000000000000001, 
    "start_at": -1719, 
    "description": "TempBasal: 1.1U/hour over 4min", 
    "type": "TempBasal", 
    "unit": "U/hour", 
    "end_at": -1715
  }, 
  {
    "amount": 0.42500000000000004, 
    "start_at": -1729, 
    "description": "TempBasal: 0.925U/hour over 9min", 
    "type": "TempBasal", 
    "unit": "U/hour", 
    "end_at": -1720
  }, 
  {
    "amount": 1.0, 
    "start_at": -3489, 
    "description": "TempBasal: 1.5U/hour over 30min", 
    "type": "TempBasal", 
    "unit": "U/hour", 
    "end_at": -3459
  }, 
  {
    "amount": 0.8, 
    "start_at": -3504, 
    "description": "TempBasal: 1.3U/hour over 14min", 
    "type": "TempBasal", 
    "unit": "U/hour", 
    "end_at": -3490
  }, 
  {
    "amount": 0.75, 
    "start_at": -3529, 
    "description": "TempBasal: 1.25U/hour over 4min", 
    "type": "TempBasal", 
    "unit": "U/hour", 
    "end_at": -3525
  }, 
  {
    "amount": 0.625, 
    "start_at": -3539, 
    "description": "TempBasal: 1.125U/hour over 10min", 
    "type": "TempBasal", 
    "unit": "U/hour", 
    "end_at": -3529
  }, 
  {
    "amount": 0.35, 
    "start_at": -3544, 
    "description": "TempBasal: 0.85U/hour over 5min", 
    "type": "TempBasal", 
    "unit": "U/hour", 
    "end_at": -3539
  }, 
  {
    "amount": -0.5, 
    "start_at": -3554, 
    "description": "TempBasal: 0.0U/hour over 10min", 
    "type": "TempBasal", 
    "unit": "U/hour", 
    "end_at": -3544
  }, 
  {
    "amount": -0.5, 
    "start_at": -3559, 
    "description": "TempBasal: 0.0U/hour over 4min", 
    "type": "TempBasal", 
    "unit": "U/hour", 
    "end_at": -3555
  }, 
  {
    "amount": -0.5, 
    "start_at": -3564, 
    "description": "TempBasal: 0.0U/hour over 4min", 
    "type": "TempBasal", 
    "unit": "U/hour", 
    "end_at": -3560
  }, 
  {
    "amount": -0.5, 
    "start_at": -3569, 
    "description": "TempBasal: 0.0U/hour over 5min", 
    "type": "TempBasal", 
    "unit": "U/hour", 
    "end_at": -3564
  }, 
  {
    "amount": -0.5, 
    "start_at": -3574, 
    "description": "TempBasal: 0.0U/hour over 4min", 
    "type": "TempBasal", 
    "unit": "U/hour", 
    "end_at": -3570
  }, 
  {
    "amount": -0.4, 
    "start_at": -3579, 
    "description": "TempBasal: 0.1U/hour over 5min", 
    "type": "TempBasal", 
    "unit": "U/hour", 
    "end_at": -3574
  }, 
  {
    "amount": -0.5, 
    "start_at": -3609, 
    "description": "TempBasal: 0.0U/hour over 24min", 
    "type": "TempBasal", 
    "unit": "U/hour", 
    "end_at": -3585
  }, 
  {
    "amount": -0.4, 
    "start_at": -3614, 
    "description": "TempBasal: 0.1U/hour over 4min", 
    "type": "TempBasal", 
    "unit": "U/hour", 
    "end_at": -3610
  }, 
  {
    "amount": -0.25, 
    "start_at": -3624, 
    "description": "TempBasal: 0.25U/hour over 5min", 
    "type": "TempBasal", 
    "unit": "U/hour", 
    "end_at": -3619
  }, 
  {
    "amount": 0.675, 
    "start_at": -3859, 
    "description": "TempBasal: 1.175U/hour over 30min", 
    "type": "TempBasal", 
    "unit": "U/hour", 
    "end_at": -3829
  }, 
  {
    "amount": 0.6000000000000001, 
    "start_at": -3869, 
    "description": "TempBasal: 1.1U/hour over 10min", 
    "type": "TempBasal", 
    "unit": "U/hour", 
    "end_at": -3859
  }, 
  {
    "amount": 0.35, 
    "start_at": -3889, 
    "description": "TempBasal: 0.85U/hour over 19min", 
    "type": "TempBasal", 
    "unit": "U/hour", 
    "end_at": -3870
  }, 
  {
    "amount": -0.375, 
    "start_at": -3914, 
    "description": "TempBasal: 0.125U/hour over 15min", 
    "type": "TempBasal", 
    "unit": "U/hour", 
    "end_at": -3899
  }, 
  {
    "amount": 0.4, 
    "start_at": -3954, 
    "description": "TempBasal: 0.9U/hour over 15min", 
    "type": "TempBasal", 
    "unit": "U/hour", 
    "end_at": -3939
  }, 
  {
    "amount": 1.0, 
    "start_at": -4049, 
    "description": "TempBasal: 1.5U/hour over 10min", 
    "type": "TempBasal", 
    "unit": "U/hour", 
    "end_at": -4039
  }, 
  {
    "amount": 1.0, 
    "start_at": -4074, 
    "description": "TempBasal: 1.5U/hour over 20min", 
    "type": "TempBasal", 
    "unit": "U/hour", 
    "end_at": -4054
  }, 
  {
    "amount": 1.0, 
    "start_at": -4109, 
    "description": "TempBasal: 1.5U/hour over 30min", 
    "type": "TempBasal", 
    "unit": "U/hour", 
    "end_at": -4079
  }, 
  {
    "amount": 0.925, 
    "start_at": -4144, 
    "description": "TempBasal: 1.425U/hour over 20min", 
    "type": "TempBasal", 
    "unit": "U/hour", 
    "end_at": -4124
  }, 
  {
    "amount": 1.0, 
    "start_at": -4274, 
    "description": "TempBasal: 1.5U/hour over 15min", 
    "type": "TempBasal", 
    "unit": "U/hour", 
    "end_at": -4259
  }, 
  {
    "amount": 1.0, 
    "start_at": -4404, 
    "description": "TempBasal: 1.5U/hour over 4min", 
    "type": "TempBasal", 
    "unit": "U/hour", 
    "end_at": -4400
  }, 
  {
    "amount": 1.0, 
    "start_at": -4424, 
    "description": "TempBasal: 1.5U/hour over 15min", 
    "type": "TempBasal", 
    "unit": "U/hour", 
    "end_at": -4409
  }, 
  {
    "amount": 1.0, 
    "start_at": -4459, 
    "description": "TempBasal: 1.5U/hour over 5min", 
    "type": "TempBasal", 
    "unit": "U/hour", 
    "end_at": -4454
  }, 
  {
    "amount": 1.0, 
    "start_at": -4499, 
    "description": "TempBasal: 1.5U/hour over 19min", 
    "type": "TempBasal", 
    "unit": "U/hour", 
    "end_at": -4480
  }, 
  {
    "amount": 1.0, 
    "start_at": -4534, 
    "description": "TempBasal: 1.5U/hour over 30min", 
    "type": "TempBasal", 
    "unit": "U/hour", 
    "end_at": -4504
  }
]