[
  {
    "direction": "SingleUp", 
    "noise": 1, 
    "dateString": "Mon Nov 16 11:32:44 PST 2015", 
    "sgv": 136, 
    "date": 1447702364000, 
    "unfiltered": 147936, 
    "rssi": 170, 
    "device": "dexcom", 
    "filtered": 131264, 
    "_id": "564a2f9807f60885b343da73", 
    "type": "sgv"
  }, 
  {
    "direction": "SingleUp", 
    "noise": 1, 
    "dateString": "Mon Nov 16 11:27:44 PST 2015", 
    "sgv": 124, 
    "date": 1447702064000, 
    "unfiltered": 138336, 
    "rssi": 185, 
    "device": "dexcom", 
    "filtered": 121248, 
    "_id": "564a2e6607f60885b343da72", 
    "type": "sgv"
  }, 
  {
    "direction": "FortyFiveUp", 
    "noise": 1, 
    "dateString": "Mon Nov 16 11:22:44 PST 2015", 
    "sgv": 111, 
    "date": 1447701764000, 
    "unfiltered": 127664, 
    "rssi": 185, 
    "device": "dexcom", 
    "filtered": 113312, 
    "_id": "564a2d3907f60885b343da71", 
    "type": "sgv"
  }, 
  {
    "direction": "Flat", 
    "noise": 1, 
    "dateString": "Mon Nov 16 11:17:44 PST 2015", 
    "sgv": 97, 
    "date": 1447701464000, 
    "unfiltered": 116128, 
    "rssi": 181, 
    "device": "dexcom", 
    "filtered": 107904, 
    "_id": "564a2c0c07f60885b343da70", 
    "type": "sgv"
  }, 
  {
    "direction": "Flat", 
    "noise": 1, 
    "dateString": "Mon Nov 16 11:12:44 PST 2015", 
    "sgv": 90, 
    "date": 1447701164000, 
    "unfiltered": 110544, 
    "rssi": 180, 
    "device": "dexcom", 
    "filtered": 105056, 
    "_id": "564a2ae007f60885b343da6f", 
    "type": "sgv"
  }, 
  {
    "direction": "Flat", 
    "noise": 1, 
    "dateString": "Mon Nov 16 11:07:44 PST 2015", 
    "sgv": 86, 
    "date": 1447700864000, 
    "unfiltered": 107184, 
    "rssi": 181, 
    "device": "dexcom", 
    "filtered": 104432, 
    "_id": "564a29b507f60885b343da6e", 
    "type": "sgv"
  }, 
  {
    "direction": "Flat", 
    "noise": 1, 
    "dateString": "Mon Nov 16 11:02:44 PST 2015", 
    "sgv": 81, 
    "date": 1447700564000, 
    "unfiltered": 103552, 
    "rssi": 181, 
    "device": "dexcom", 
    "filtered": 105584, 
    "_id": "564a288807f60885b343da6d", 
    "type": "sgv"
  }, 
  {
    "direction": "Flat", 
    "noise": 1, 
    "dateString": "Mon Nov 16 10:57:44 PST 2015", 
    "sgv": 82, 
    "date": 1447700264000, 
    "unfiltered": 104592, 
    "rssi": 184, 
    "device": "dexcom", 
    "filtered": 107520, 
    "_id": "564a275d07f60885b343da6c", 
    "type": "sgv"
  }, 
  {
    "direction": "Flat", 
    "noise": 1, 
    "dateString": "Mon Nov 16 10:52:44 PST 2015", 
    "sgv": 83, 
    "date": 1447699964000, 
    "unfiltered": 105360, 
    "rssi": 181, 
    "device": "dexcom", 
    "filtered": 109664, 
    "_id": "564a263107f60885b343da6b", 
    "type": "sgv"
  }, 
  {
    "direction": "Flat", 
    "noise": 1, 
    "dateString": "Mon Nov 16 10:47:44 PST 2015", 
    "sgv": 89, 
    "date": 1447699664000, 
    "unfiltered": 109936, 
    "rssi": 182, 
    "device": "dexcom", 
    "filtered": 112192, 
    "_id": "564a250407f60885b343da6a", 
    "type": "sgv"
  }
]