[
  {
    "direction": "Flat", 
    "noise": 1, 
    "dateString": "Tue Nov 17 23:27:31 PST 2015", 
    "sgv": 151, 
    "date": 1447831651000, 
    "unfiltered": 170528, 
    "rssi": 191, 
    "device": "dexcom", 
    "filtered": 167584, 
    "_id": "564c289d07f60885b343dc22", 
    "type": "sgv"
  }, 
  {
    "direction": "Flat", 
    "noise": 1, 
    "dateString": "Tue Nov 17 23:22:31 PST 2015", 
    "sgv": 149, 
    "date": 1447831351000, 
    "unfiltered": 169376, 
    "rssi": 180, 
    "device": "dexcom", 
    "filtered": 165184, 
    "_id": "564c277107f60885b343dc21", 
    "type": "sgv"
  }, 
  {
    "direction": "Flat", 
    "noise": 1, 
    "dateString": "Tue Nov 17 23:17:31 PST 2015", 
    "sgv": 147, 
    "date": 1447831051000, 
    "unfiltered": 166944, 
    "rssi": 188, 
    "device": "dexcom", 
    "filtered": 163328, 
    "_id": "564c264507f60885b343dc20", 
    "type": "sgv"
  }, 
  {
    "direction": "Flat", 
    "noise": 1, 
    "dateString": "Tue Nov 17 23:12:31 PST 2015", 
    "sgv": 144, 
    "date": 1447830751000, 
    "unfiltered": 164576, 
    "rssi": 196, 
    "device": "dexcom", 
    "filtered": 162336, 
    "_id": "564c251707f60885b343dc1f", 
    "type": "sgv"
  }, 
  {
    "direction": "Flat", 
    "noise": 1, 
    "dateString": "Tue Nov 17 23:07:31 PST 2015", 
    "sgv": 141, 
    "date": 1447830451000, 
    "unfiltered": 162304, 
    "rssi": 196, 
    "device": "dexcom", 
    "filtered": 161728, 
    "_id": "564c23ec07f60885b343dc1e", 
    "type": "sgv"
  }, 
  {
    "direction": "Flat", 
    "noise": 1, 
    "dateString": "Tue Nov 17 23:02:31 PST 2015", 
    "sgv": 140, 
    "date": 1447830151000, 
    "unfiltered": 161120, 
    "rssi": 196, 
    "device": "dexcom", 
    "filtered": 161056, 
    "_id": "564c22c607f60885b343dc1d", 
    "type": "sgv"
  }, 
  {
    "direction": "Flat", 
    "noise": 1, 
    "dateString": "Tue Nov 17 22:57:31 PST 2015", 
    "sgv": 141, 
    "date": 1447829851000, 
    "unfiltered": 161792, 
    "rssi": 196, 
    "device": "dexcom", 
    "filtered": 160832, 
    "_id": "564c219407f60885b343dc1c", 
    "type": "sgv"
  }, 
  {
    "direction": "Flat", 
    "noise": 1, 
    "dateString": "Tue Nov 17 22:52:31 PST 2015", 
    "sgv": 142, 
    "date": 1447829551000, 
    "unfiltered": 162400, 
    "rssi": 196, 
    "device": "dexcom", 
    "filtered": 162656, 
    "_id": "564c207607f60885b343dc1b", 
    "type": "sgv"
  }, 
  {
    "direction": "Flat", 
    "noise": 1, 
    "dateString": "Tue Nov 17 22:47:31 PST 2015", 
    "sgv": 142, 
    "date": 1447829251000, 
    "unfiltered": 162816, 
    "rssi": 195, 
    "device": "dexcom", 
    "filtered": 167136, 
    "_id": "564c1f4107f60885b343dc1a", 
    "type": "sgv"
  }, 
  {
    "direction": "FortyFiveDown", 
    "noise": 1, 
    "dateString": "Tue Nov 17 22:42:31 PST 2015", 
    "sgv": 142, 
    "date": 1447828951000, 
    "unfiltered": 162528, 
    "rssi": 195, 
    "device": "dexcom", 
    "filtered": 172544, 
    "_id": "564c1e0f07f60885b343dc19", 
    "type": "sgv"
  }
]