[
  {
    "direction": "Flat", 
    "noise": 1, 
    "dateString": "Wed Jan 06 01:31:03 PST 2016", 
    "sgv": 105, 
    "date": 1452072663000, 
    "unfiltered": 118736, 
    "rssi": 184, 
    "device": "dexcom", 
    "filtered": 119904, 
    "_id": "568cdef807f60885b3441f4c", 
    "type": "sgv"
  }, 
  {
    "direction": "Flat", 
    "noise": 1, 
    "dateString": "Wed Jan 06 01:26:03 PST 2016", 
    "sgv": 105, 
    "date": 1452072363000, 
    "unfiltered": 119344, 
    "rssi": 181, 
    "device": "dexcom", 
    "filtered": 119360, 
    "_id": "568cddca07f60885b3441f4b", 
    "type": "sgv"
  }, 
  {
    "direction": "Flat", 
    "noise": 1, 
    "dateString": "Wed Jan 06 01:21:03 PST 2016", 
    "sgv": 106, 
    "date": 1452072063000, 
    "unfiltered": 120016, 
    "rssi": 182, 
    "device": "dexcom", 
    "filtered": 118144, 
    "_id": "568cdc9f07f60885b3441f4a", 
    "type": "sgv"
  }, 
  {
    "direction": "Flat", 
    "noise": 1, 
    "dateString": "Wed Jan 06 01:16:03 PST 2016", 
    "sgv": 106, 
    "date": 1452071763000, 
    "unfiltered": 119456, 
    "rssi": 183, 
    "device": "dexcom", 
    "filtered": 117008, 
    "_id": "568cdb7407f60885b3441f49", 
    "type": "sgv"
  }, 
  {
    "direction": "Flat", 
    "noise": 1, 
    "dateString": "Wed Jan 06 01:11:04 PST 2016", 
    "sgv": 104, 
    "date": 1452071464000, 
    "unfiltered": 118064, 
    "rssi": 183, 
    "device": "dexcom", 
    "filtered": 116720, 
    "_id": "568cda4707f60885b3441f48", 
    "type": "sgv"
  }, 
  {
    "direction": "Flat", 
    "noise": 1, 
    "dateString": "Wed Jan 06 01:06:03 PST 2016", 
    "sgv": 103, 
    "date": 1452071163000, 
    "unfiltered": 116784, 
    "rssi": 185, 
    "device": "dexcom", 
    "filtered": 117360, 
    "_id": "568cd91b07f60885b3441f47", 
    "type": "sgv"
  }, 
  {
    "direction": "Flat", 
    "noise": 1, 
    "dateString": "Wed Jan 06 01:01:03 PST 2016", 
    "sgv": 102, 
    "date": 1452070863000, 
    "unfiltered": 116256, 
    "rssi": 194, 
    "device": "dexcom", 
    "filtered": 118448, 
    "_id": "568cd7ef07f60885b3441f46", 
    "type": "sgv"
  }, 
  {
    "direction": "Flat", 
    "noise": 1, 
    "dateString": "Wed Jan 06 00:56:03 PST 2016", 
    "sgv": 104, 
    "date": 1452070563000, 
    "unfiltered": 117760, 
    "rssi": 191, 
    "device": "dexcom", 
    "filtered": 119472, 
    "_id": "568cd6c307f60885b3441f45", 
    "type": "sgv"
  }, 
  {
    "direction": "Flat", 
    "noise": 1, 
    "dateString": "Wed Jan 06 00:51:03 PST 2016", 
    "sgv": 105, 
    "date": 1452070263000, 
    "unfiltered": 119040, 
    "rssi": 191, 
    "device": "dexcom", 
    "filtered": 120240, 
    "_id": "568cd59707f60885b3441f44", 
    "type": "sgv"
  }, 
  {
    "direction": "Flat", 
    "noise": 1, 
    "dateString": "Wed Jan 06 00:46:03 PST 2016", 
    "sgv": 107, 
    "date": 1452069963000, 
    "unfiltered": 120016, 
    "rssi": 191, 
    "device": "dexcom", 
    "filtered": 120960, 
    "_id": "568cd46b07f60885b3441f43", 
    "type": "sgv"
  }
]