[
  {
    "trend_arrow": "FLAT", 
    "system_time": "2015-11-25T08:04:29", 
    "display_time": "2015-11-25T00:06:39", 
    "glucose": 148
  }, 
  {
    "trend_arrow": "FLAT", 
    "system_time": "2015-11-25T07:59:29", 
    "display_time": "2015-11-25T00:01:39", 
    "glucose": 150
  }, 
  {
    "trend_arrow": "FLAT", 
    "system_time": "2015-11-25T07:54:29", 
    "display_time": "2015-11-24T23:56:39", 
    "glucose": 159
  }, 
  {
    "trend_arrow": "FLAT", 
    "system_time": "2015-11-25T07:49:29", 
    "display_time": "2015-11-24T23:51:39", 
    "glucose": 164
  }, 
  {
    "trend_arrow": "FLAT", 
    "system_time": "2015-11-25T07:44:29", 
    "display_time": "2015-11-24T23:46:39", 
    "glucose": 163
  }
]