[
  {
    "direction": "Flat", 
    "noise": 1, 
    "dateString": "Tue Dec 22 03:05:57 PST 2015", 
    "sgv": 143, 
    "date": 1450782357000, 
    "unfiltered": 136416, 
    "rssi": 193, 
    "device": "dexcom", 
    "filtered": 132544, 
    "_id": "56792ea507f60885b3440c75", 
    "type": "sgv"
  }, 
  {
    "direction": "Flat", 
    "noise": 1, 
    "dateString": "Tue Dec 22 03:00:57 PST 2015", 
    "sgv": 138, 
    "date": 1450782057000, 
    "unfiltered": 133632, 
    "rssi": 193, 
    "device": "dexcom", 
    "filtered": 131264, 
    "_id": "56792d7807f60885b3440c74", 
    "type": "sgv"
  }, 
  {
    "direction": "Flat", 
    "noise": 1, 
    "dateString": "Tue Dec 22 02:55:57 PST 2015", 
    "sgv": 136, 
    "date": 1450781757000, 
    "unfiltered": 131840, 
    "rssi": 194, 
    "device": "dexcom", 
    "filtered": 130608, 
    "_id": "56792c4d07f60885b3440c73", 
    "type": "sgv"
  }, 
  {
    "direction": "Flat", 
    "noise": 1, 
    "dateString": "Tue Dec 22 02:50:57 PST 2015", 
    "sgv": 133, 
    "date": 1450781457000, 
    "unfiltered": 130272, 
    "rssi": 195, 
    "device": "dexcom", 
    "filtered": 130320, 
    "_id": "56792b2707f60885b3440c72", 
    "type": "sgv"
  }, 
  {
    "direction": "Flat", 
    "noise": 1, 
    "dateString": "Tue Dec 22 02:45:57 PST 2015", 
    "sgv": 134, 
    "date": 1450781157000, 
    "unfiltered": 130912, 
    "rssi": 181, 
    "device": "dexcom", 
    "filtered": 130336, 
    "_id": "567929f307f60885b3440c71", 
    "type": "sgv"
  }, 
  {
    "direction": "Flat", 
    "noise": 1, 
    "dateString": "Tue Dec 22 02:40:57 PST 2015", 
    "sgv": 134, 
    "date": 1450780857000, 
    "unfiltered": 130384, 
    "rssi": 181, 
    "device": "dexcom", 
    "filtered": 130736, 
    "_id": "567928c707f60885b3440c70", 
    "type": "sgv"
  }, 
  {
    "direction": "Flat", 
    "noise": 1, 
    "dateString": "Tue Dec 22 02:35:57 PST 2015", 
    "sgv": 134, 
    "date": 1450780557000, 
    "unfiltered": 130416, 
    "rssi": 181, 
    "device": "dexcom", 
    "filtered": 131520, 
    "_id": "567927b507f60885b3440c6f", 
    "type": "sgv"
  }, 
  {
    "direction": "Flat", 
    "noise": 1, 
    "dateString": "Tue Dec 22 02:30:57 PST 2015", 
    "sgv": 134, 
    "date": 1450780257000, 
    "unfiltered": 130944, 
    "rssi": 182, 
    "device": "dexcom", 
    "filtered": 132480, 
    "_id": "5679267007f60885b3440c6e", 
    "type": "sgv"
  }, 
  {
    "direction": "Flat", 
    "noise": 1, 
    "dateString": "Tue Dec 22 02:25:57 PST 2015", 
    "sgv": 136, 
    "date": 1450779957000, 
    "unfiltered": 131744, 
    "rssi": 182, 
    "device": "dexcom", 
    "filtered": 133504, 
    "_id": "5679255f07f60885b3440c6d", 
    "type": "sgv"
  }, 
  {
    "direction": "Flat", 
    "noise": 1, 
    "dateString": "Tue Dec 22 02:20:57 PST 2015", 
    "sgv": 138, 
    "date": 1450779657000, 
    "unfiltered": 133184, 
    "rssi": 182, 
    "device": "dexcom", 
    "filtered": 134944, 
    "_id": "5679241707f60885b3440c6c", 
    "type": "sgv"
  }
]