[
  {
    "direction": "Flat", 
    "noise": 1, 
    "dateString": "Thu Dec 10 02:45:49 PST 2015", 
    "sgv": 94, 
    "date": 1449744349000, 
    "unfiltered": 115568, 
    "rssi": 194, 
    "device": "dexcom", 
    "filtered": 116992, 
    "_id": "5669582207f60885b343fca9", 
    "type": "sgv"
  }, 
  {
    "direction": "Flat", 
    "noise": 1, 
    "dateString": "Thu Dec 10 02:40:49 PST 2015", 
    "sgv": 95, 
    "date": 1449744049000, 
    "unfiltered": 116416, 
    "rssi": 194, 
    "device": "dexcom", 
    "filtered": 118464, 
    "_id": "566956f607f60885b343fca8", 
    "type": "sgv"
  }, 
  {
    "direction": "Flat", 
    "noise": 1, 
    "dateString": "Thu Dec 10 02:35:49 PST 2015", 
    "sgv": 97, 
    "date": 1449743749000, 
    "unfiltered": 117792, 
    "rssi": 195, 
    "device": "dexcom", 
    "filtered": 120400, 
    "_id": "566955ca07f60885b343fca7", 
    "type": "sgv"
  }, 
  {
    "direction": "Flat", 
    "noise": 1, 
    "dateString": "Thu Dec 10 02:30:49 PST 2015", 
    "sgv": 99, 
    "date": 1449743449000, 
    "unfiltered": 119104, 
    "rssi": 196, 
    "device": "dexcom", 
    "filtered": 122736, 
    "_id": "5669549e07f60885b343fca6", 
    "type": "sgv"
  }, 
  {
    "direction": "Flat", 
    "noise": 1, 
    "dateString": "Thu Dec 10 02:25:49 PST 2015", 
    "sgv": 102, 
    "date": 1449743149000, 
    "unfiltered": 121536, 
    "rssi": 196, 
    "device": "dexcom", 
    "filtered": 125568, 
    "_id": "5669537207f60885b343fca5", 
    "type": "sgv"
  }, 
  {
    "direction": "Flat", 
    "noise": 1, 
    "dateString": "Thu Dec 10 02:20:49 PST 2015", 
    "sgv": 105, 
    "date": 1449742849000, 
    "unfiltered": 124400, 
    "rssi": 193, 
    "device": "dexcom", 
    "filtered": 128736, 
    "_id": "5669524507f60885b343fca4", 
    "type": "sgv"
  }, 
  {
    "direction": "Flat", 
    "noise": 1, 
    "dateString": "Thu Dec 10 02:15:49 PST 2015", 
    "sgv": 108, 
    "date": 1449742549000, 
    "unfiltered": 126640, 
    "rssi": 193, 
    "device": "dexcom", 
    "filtered": 131712, 
    "_id": "5669511b07f60885b343fca3", 
    "type": "sgv"
  }, 
  {
    "direction": "Flat", 
    "noise": 1, 
    "dateString": "Thu Dec 10 02:10:49 PST 2015", 
    "sgv": 112, 
    "date": 1449742249000, 
    "unfiltered": 129328, 
    "rssi": 193, 
    "device": "dexcom", 
    "filtered": 133984, 
    "_id": "56694fed07f60885b343fca2", 
    "type": "sgv"
  }, 
  {
    "direction": "Flat", 
    "noise": 1, 
    "dateString": "Thu Dec 10 02:05:49 PST 2015", 
    "sgv": 117, 
    "date": 1449741949000, 
    "unfiltered": 133408, 
    "rssi": 193, 
    "device": "dexcom", 
    "filtered": 135328, 
    "_id": "56694ec307f60885b343fca1", 
    "type": "sgv"
  }, 
  {
    "direction": "Flat", 
    "noise": 1, 
    "dateString": "Thu Dec 10 02:00:49 PST 2015", 
    "sgv": 119, 
    "date": 1449741649000, 
    "unfiltered": 134912, 
    "rssi": 191, 
    "device": "dexcom", 
    "filtered": 136064, 
    "_id": "56694d9607f60885b343fca0", 
    "type": "sgv"
  }
]