[
  {
    "direction": "Flat", 
    "noise": 1, 
    "dateString": "Mon Nov 30 03:02:30 PST 2015", 
    "sgv": 195, 
    "date": 1448881350000, 
    "unfiltered": 218176, 
    "rssi": 198, 
    "device": "dexcom", 
    "filtered": 223360, 
    "_id": "565c2cf807f60885b343ed1a", 
    "type": "sgv"
  }, 
  {
    "direction": "Flat", 
    "noise": 1, 
    "dateString": "Mon Nov 30 02:57:30 PST 2015", 
    "sgv": 198, 
    "date": 1448881050000, 
    "unfiltered": 220480, 
    "rssi": 194, 
    "device": "dexcom", 
    "filtered": 228160, 
    "_id": "565c2bc907f60885b343ed19", 
    "type": "sgv"
  }, 
  {
    "direction": "Flat", 
    "noise": 1, 
    "dateString": "Mon Nov 30 02:52:30 PST 2015", 
    "sgv": 202, 
    "date": 1448880750000, 
    "unfiltered": 224544, 
    "rssi": 195, 
    "device": "dexcom", 
    "filtered": 232352, 
    "_id": "565c2a9c07f60885b343ed18", 
    "type": "sgv"
  }, 
  {
    "direction": "Flat", 
    "noise": 1, 
    "dateString": "Mon Nov 30 02:47:30 PST 2015", 
    "sgv": 208, 
    "date": 1448880450000, 
    "unfiltered": 229696, 
    "rssi": 194, 
    "device": "dexcom", 
    "filtered": 235168, 
    "_id": "565c296f07f60885b343ed17", 
    "type": "sgv"
  }, 
  {
    "direction": "Flat", 
    "noise": 1, 
    "dateString": "Mon Nov 30 02:42:30 PST 2015", 
    "sgv": 214, 
    "date": 1448880150000, 
    "unfiltered": 234816, 
    "rssi": 194, 
    "device": "dexcom", 
    "filtered": 236832, 
    "_id": "565c284607f60885b343ed16", 
    "type": "sgv"
  }, 
  {
    "direction": "Flat", 
    "noise": 1, 
    "dateString": "Mon Nov 30 02:37:30 PST 2015", 
    "sgv": 216, 
    "date": 1448879850000, 
    "unfiltered": 236640, 
    "rssi": 183, 
    "device": "dexcom", 
    "filtered": 237888, 
    "_id": "565c272507f60885b343ed15", 
    "type": "sgv"
  }, 
  {
    "direction": "Flat", 
    "noise": 1, 
    "dateString": "Mon Nov 30 02:32:30 PST 2015", 
    "sgv": 215, 
    "date": 1448879550000, 
    "unfiltered": 236480, 
    "rssi": 182, 
    "device": "dexcom", 
    "filtered": 238944, 
    "_id": "565c25ec07f60885b343ed14", 
    "type": "sgv"
  }, 
  {
    "direction": "Flat", 
    "noise": 1, 
    "dateString": "Mon Nov 30 02:27:30 PST 2015", 
    "sgv": 218, 
    "date": 1448879250000, 
    "unfiltered": 239072, 
    "rssi": 195, 
    "device": "dexcom", 
    "filtered": 240800, 
    "_id": "565c24c007f60885b343ed13", 
    "type": "sgv"
  }, 
  {
    "direction": "FortyFiveDown", 
    "noise": 1, 
    "dateString": "Mon Nov 30 02:22:30 PST 2015", 
    "sgv": 220, 
    "date": 1448878950000, 
    "unfiltered": 240736, 
    "rssi": 195, 
    "device": "dexcom", 
    "filtered": 244768, 
    "_id": "565c239207f60885b343ed12", 
    "type": "sgv"
  }, 
  {
    "direction": "FortyFiveDown", 
    "noise": 1, 
    "dateString": "Mon Nov 30 02:17:30 PST 2015", 
    "sgv": 223, 
    "date": 1448878650000, 
    "unfiltered": 243136, 
    "rssi": 195, 
    "device": "dexcom", 
    "filtered": 251744, 
    "_id": "565c226b07f60885b343ed11", 
    "type": "sgv"
  }
]