[
  {
    "direction": "Flat", 
    "noise": 1, 
    "sysTime": "2016-01-15T06:35:49.527-0800", 
    "xDrip_calculated_value": 106, 
    "xDrip_raw": 144, 
    "dateString": "2016-01-15T06:35:49.527-0800", 
    "sgv": 106, 
    "date": 1452868549527, 
    "xDrip_filtered": 144, 
    "xDrip_age_adjusted_raw_value": 144, 
    "unfiltered": 144000, 
    "rssi": 100, 
    "device": "xDrip-DexcomShare", 
    "filtered": 144000, 
    "xDrip_calculated_current_slope": 0, 
    "_id": "569903fd07f60885b3442f93", 
    "type": "sgv"
  }, 
  {
    "direction": "Flat", 
    "noise": 1, 
    "sysTime": "2016-01-15T06:30:49.557-0800", 
    "xDrip_calculated_value": 106, 
    "xDrip_raw": 143, 
    "dateString": "2016-01-15T06:30:49.557-0800", 
    "sgv": 106, 
    "date": 1452868249557, 
    "xDrip_filtered": 145, 
    "xDrip_age_adjusted_raw_value": 143, 
    "unfiltered": 143000, 
    "rssi": 100, 
    "device": "xDrip-DexcomShare", 
    "filtered": 145000, 
    "xDrip_calculated_current_slope": -3.335034200775729e-06, 
    "_id": "569902b707f60885b3442f90", 
    "type": "sgv"
  }, 
  {
    "direction": "Flat", 
    "noise": 1, 
    "sysTime": "2016-01-15T06:25:49.710-0800", 
    "xDrip_calculated_value": 107, 
    "xDrip_raw": 144, 
    "dateString": "2016-01-15T06:25:49.710-0800", 
    "sgv": 107, 
    "date": 1452867949710, 
    "xDrip_filtered": 145, 
    "xDrip_age_adjusted_raw_value": 144, 
    "unfiltered": 144000, 
    "rssi": 100, 
    "device": "xDrip-DexcomShare", 
    "filtered": 145000, 
    "xDrip_calculated_current_slope": -6.6640676802713605e-06, 
    "_id": "5699018b07f60885b3442f8f", 
    "type": "sgv"
  }, 
  {
    "direction": "Flat", 
    "noise": 1, 
    "sysTime": "2016-01-15T06:20:49.593-0800", 
    "xDrip_calculated_value": 109, 
    "xDrip_raw": 146, 
    "dateString": "2016-01-15T06:20:49.593-0800", 
    "sgv": 109, 
    "date": 1452867649593, 
    "xDrip_filtered": 147, 
    "xDrip_age_adjusted_raw_value": 146, 
    "unfiltered": 146000, 
    "rssi": 100, 
    "device": "xDrip-DexcomShare", 
    "filtered": 147000, 
    "xDrip_calculated_current_slope": 0, 
    "_id": "5699007707f60885b3442f8e", 
    "type": "sgv"
  }, 
  {
    "direction": "Flat", 
    "noise": 1, 
    "sysTime": "2016-01-15T06:15:48.769-0800", 
    "xDrip_calculated_value": 109, 
    "xDrip_raw": 146, 
    "dateString": "2016-01-15T06:15:48.769-0800", 
    "sgv": 109, 
    "date": 1452867348769, 
    "xDrip_filtered": 148, 
    "xDrip_age_adjusted_raw_value": 146, 
    "unfiltered": 146000, 
    "rssi": 100, 
    "device": "xDrip-DexcomShare", 
    "filtered": 148000, 
    "xDrip_calculated_current_slope": -3.342257159950401e-06, 
    "_id": "5698ff3507f60885b3442f8d", 
    "type": "sgv"
  }, 
  {
    "direction": "Flat", 
    "noise": 1, 
    "sysTime": "2016-01-15T06:10:49.570-0800", 
    "xDrip_calculated_value": 110, 
    "xDrip_raw": 147, 
    "dateString": "2016-01-15T06:10:49.570-0800", 
    "sgv": 110, 
    "date": 1452867049570, 
    "xDrip_filtered": 150, 
    "xDrip_age_adjusted_raw_value": 147, 
    "unfiltered": 147000, 
    "rssi": 100, 
    "device": "xDrip-DexcomShare", 
    "filtered": 150000, 
    "xDrip_calculated_current_slope": -3.3237498545859438e-06, 
    "_id": "5698fe1f07f60885b3442f8a", 
    "type": "sgv"
  }, 
  {
    "direction": "Flat", 
    "noise": 1, 
    "sysTime": "2016-01-15T06:05:48.705-0800", 
    "xDrip_calculated_value": 111, 
    "xDrip_raw": 148, 
    "dateString": "2016-01-15T06:05:48.705-0800", 
    "sgv": 111, 
    "date": 1452866748705, 
    "xDrip_filtered": 151, 
    "xDrip_age_adjusted_raw_value": 148, 
    "unfiltered": 148000, 
    "rssi": 100, 
    "device": "xDrip-DexcomShare", 
    "filtered": 151000, 
    "xDrip_calculated_current_slope": -6.689612035949975e-06, 
    "_id": "5698fcd507f60885b3442f88", 
    "type": "sgv"
  }, 
  {
    "direction": "Flat", 
    "noise": 1, 
    "sysTime": "2016-01-15T06:00:49.734-0800", 
    "xDrip_calculated_value": 113, 
    "xDrip_raw": 150, 
    "dateString": "2016-01-15T06:00:49.734-0800", 
    "sgv": 113, 
    "date": 1452866449734, 
    "xDrip_filtered": 152, 
    "xDrip_age_adjusted_raw_value": 150, 
    "unfiltered": 150000, 
    "rssi": 100, 
    "device": "xDrip-DexcomShare", 
    "filtered": 152000, 
    "xDrip_calculated_current_slope": -3.343430493423472e-06, 
    "_id": "5698fbd107f60885b3442f87", 
    "type": "sgv"
  }, 
  {
    "direction": "Flat", 
    "noise": 1, 
    "sysTime": "2016-01-15T05:55:50.640-0800", 
    "xDrip_calculated_value": 114, 
    "xDrip_raw": 151, 
    "dateString": "2016-01-15T05:55:50.640-0800", 
    "sgv": 114, 
    "date": 1452866150640, 
    "xDrip_filtered": 153, 
    "xDrip_age_adjusted_raw_value": 151, 
    "unfiltered": 151000, 
    "rssi": 100, 
    "device": "xDrip-DexcomShare", 
    "filtered": 153000, 
    "xDrip_calculated_current_slope": -6.626707619719756e-06, 
    "_id": "5698fa7c07f60885b3442f86", 
    "type": "sgv"
  }, 
  {
    "direction": "Flat", 
    "noise": 1, 
    "sysTime": "2016-01-15T05:50:48.831-0800", 
    "xDrip_calculated_value": 116, 
    "xDrip_raw": 153, 
    "dateString": "2016-01-15T05:50:48.831-0800", 
    "sgv": 116, 
    "date": 1452865848831, 
    "xDrip_filtered": 154, 
    "xDrip_age_adjusted_raw_value": 153, 
    "unfiltered": 153000, 
    "rssi": 100, 
    "device": "xDrip-DexcomShare", 
    "filtered": 154000, 
    "xDrip_calculated_current_slope": 0, 
    "_id": "5698f96c07f60885b3442f85", 
    "type": "sgv"
  }
]