{
  "pump": {
    "battery": {
      "status": "normal", 
      "voltage": 1.55
    }, 
    "status": {
      "status": "normal", 
      "timestamp": "2016-01-08T05:27:37.000Z", 
      "bolusing": false, 
      "suspended": false
    }, 
    "reservoir": 174.6, 
    "clock": "2016-01-07T21:26:32-08:00"
  }, 
  "openaps": {
    "suggested": {
      "bg": 121, 
      "temp": "absolute", 
      "snoozeBG": 111, 
      "timestamp": "2016-01-08T05:31:40.000Z", 
      "reason": "Eventual BG 111>110 but Avg. Delta 1.00 < Exp. Delta 3.6; no temp to cancel", 
      "eventualBG": 111, 
      "mealAssist": "Off: Carbs: 0 Boluses: 0 Target: 115 Deviation: -15 BGI: 3.47", 
      "tick": "+3"
    }, 
    "iob": {
      "timestamp": "2016-01-08T05:31:40.000Z", 
      "bolussnooze": 0, 
      "basaliob": -0.059, 
      "iob": -0.059, 
      "activity": -0.0077
    }, 
    "enacted": {
      "bg": 120, 
      "temp": "absolute", 
      "snoozeBG": 146, 
      "recieved": true, 
      "reason": "Eventual BG 146>110 but Delta +2 < Exp. Delta 3; cancel", 
      "rate": 0, 
      "eventualBG": 146, 
      "timestamp": "2016-01-08T05:22:12.000Z", 
      "duration": 0, 
      "mealAssist": "Off: Carbs: 0 Boluses: 0 Target: 115 Deviation: 14 BGI: 3.87", 
      "tick": "+2"
    }
  }
}