{
  "pump": {
    "battery": {
      "status": "normal", 
      "voltage": 1.43
    }, 
    "status": {
      "status": "normal", 
      "timestamp": "2015-12-11T23:13:36.000Z", 
      "bolusing": false, 
      "suspended": false
    }, 
    "reservoir": 108.5, 
    "clock": "2015-12-11T15:12:45-08:00"
  }, 
  "openaps": {
    "suggested": {
      "bg": 47, 
      "temp": "absolute", 
      "snoozeBG": 39, 
      "timestamp": "2015-12-11T23:12:19.000Z", 
      "rate": 0, 
      "reason": "BG 47<80", 
      "eventualBG": 39, 
      "duration": 30, 
      "tick": "+2"
    }, 
    "iob": {
      "timestamp": "2015-12-11T23:12:18.000Z", 
      "bolusiob": 0, 
      "iob": -0.09983751272222222, 
      "activity": -3.814814814814815e-05
    }, 
    "enacted": {
      "bg": 47, 
      "temp": "absolute", 
      "snoozeBG": 39, 
      "recieved": true, 
      "reason": "BG 47<80", 
      "rate": 0, 
      "eventualBG": 39, 
      "timestamp": "2015-12-11T23:12:36.000Z", 
      "duration": 30, 
      "tick": "+2"
    }
  }
}