{
  "pump": {
    "battery": {
      "status": "normal", 
      "voltage": 1.6
    }, 
    "status": {
      "status": "normal", 
      "timestamp": "2016-01-07T13:23:42.000Z", 
      "bolusing": false, 
      "suspended": false
    }, 
    "reservoir": 68.8, 
    "clock": "2016-01-07T05:22:34-08:00"
  }, 
  "openaps": {
    "suggested": {
      "bg": 107, 
      "temp": "absolute", 
      "snoozeBG": 116, 
      "timestamp": "2016-01-07T13:21:51.000Z", 
      "reason": "Eventual BG 116>115 but Delta +1 < Exp. Delta 1.8; no temp to cancel", 
      "eventualBG": 116, 
      "mealAssist": "Off: Carbs: 0 Boluses: 0 Target: 117.5 Deviation: -3 BGI: 1.8", 
      "tick": "+1"
    }, 
    "iob": {
      "timestamp": "2016-01-07T13:21:50.000Z", 
      "bolussnooze": 0, 
      "basaliob": -0.138, 
      "iob": -0.138, 
      "activity": -0.004
    }, 
    "enacted": {
      "bg": 103, 
      "temp": "absolute", 
      "snoozeBG": 123, 
      "recieved": true, 
      "reason": "Eventual BG 123>115 but Delta +1 < Exp. Delta 1.8; cancel", 
      "rate": 0, 
      "eventualBG": 123, 
      "timestamp": "2016-01-07T13:06:58.000Z", 
      "duration": 0, 
      "mealAssist": "Off: Carbs: 0 Boluses: 0 Target: 117.5 Deviation: 2 BGI: 1.98", 
      "tick": "+1"
    }
  }
}