{
  "pump": {
    "battery": {
      "status": "normal", 
      "voltage": 1.51
    }, 
    "status": {
      "status": "normal", 
      "timestamp": "2016-01-10T19:02:37.000Z", 
      "bolusing": false, 
      "suspended": false
    }, 
    "reservoir": 94.9, 
    "clock": "2016-01-10T11:01:33-08:00"
  }, 
  "openaps": {
    "suggested": {
      "bg": 117, 
      "temp": "absolute", 
      "snoozeBG": 84, 
      "timestamp": "2016-01-10T19:01:16.000Z", 
      "rate": 0, 
      "reason": "Eventual BG 75<110, setting -0.828U/hr", 
      "eventualBG": 75, 
      "duration": 30, 
      "mealAssist": "Off: Carbs: 12 Boluses: 2 Target: 115 Deviation: 29 BGI: -7.96", 
      "tick": "+0"
    }, 
    "iob": {
      "timestamp": "2016-01-10T19:01:16.000Z", 
      "bolussnooze": 0.064, 
      "basaliob": -0.187, 
      "iob": 0.789, 
      "activity": 0.0177
    }, 
    "enacted": {
      "bg": 117, 
      "temp": "absolute", 
      "snoozeBG": 84, 
      "recieved": true, 
      "reason": "Eventual BG 75<110, setting -0.828U/hr", 
      "rate": 0, 
      "eventualBG": 75, 
      "timestamp": "2016-01-10T19:01:34.000Z", 
      "duration": 30, 
      "mealAssist": "Off: Carbs: 12 Boluses: 2 Target: 115 Deviation: 29 BGI: -7.96", 
      "tick": "+0"
    }
  }
}