{
  "pump": {
    "battery": {
      "status": "normal", 
      "voltage": 1.53
    }, 
    "status": {
      "status": "normal", 
      "timestamp": "2015-12-25T15:08:41.000Z", 
      "bolusing": false, 
      "suspended": false
    }, 
    "reservoir": 131.7, 
    "clock": "2015-12-25T07:07:40-08:00"
  }, 
  "openaps": {
    "suggested": {
      "bg": 155, 
      "temp": "absolute", 
      "snoozeBG": 112, 
      "timestamp": "2015-12-25T15:07:03.000Z", 
      "rate": 0.3, 
      "reason": "Eventual BG 112<115, setting 0.317U/hr", 
      "eventualBG": 112, 
      "duration": 30, 
      "mealAssist": "Off: Carbs: 0 Boluses: 0 Target: 122.5 Deviation: -12 BGI: 0.22", 
      "tick": -5
    }, 
    "iob": {
      "timestamp": "2015-12-25T15:07:03.000Z", 
      "bolussnooze": 0, 
      "basaliob": 0.345, 
      "iob": 0.345, 
      "activity": -0.0005
    }, 
    "enacted": {
      "bg": 155, 
      "temp": "absolute", 
      "snoozeBG": 112, 
      "recieved": true, 
      "reason": "Eventual BG 112<115, setting 0.317U/hr", 
      "rate": 0.275, 
      "eventualBG": 112, 
      "timestamp": "2015-12-25T15:07:22.000Z", 
      "duration": 30, 
      "mealAssist": "Off: Carbs: 0 Boluses: 0 Target: 122.5 Deviation: -12 BGI: 0.22", 
      "tick": -5
    }
  }
}