{
  "pump": {
    "battery": {
      "status": "normal", 
      "voltage": 1.54
    }, 
    "status": {
      "status": "normal", 
      "timestamp": "2016-01-08T11:53:38.000Z", 
      "bolusing": false, 
      "suspended": false
    }, 
    "reservoir": 169.9, 
    "clock": "2016-01-08T03:52:31-08:00"
  }, 
  "openaps": {
    "suggested": {
      "bg": 131, 
      "temp": "absolute", 
      "snoozeBG": 122, 
      "timestamp": "2016-01-08T11:51:38.000Z", 
      "rate": 0.55, 
      "reason": "Eventual BG 122>=120, no temp, setting 0.57U/hr", 
      "eventualBG": 122, 
      "duration": 30, 
      "mealAssist": "Off: Carbs: 0 Boluses: 0 Target: 115 Deviation: 3 BGI: -1.35", 
      "tick": "+1"
    }, 
    "iob": {
      "timestamp": "2016-01-08T11:51:38.000Z", 
      "bolussnooze": 0, 
      "basaliob": 0.133, 
      "iob": 0.133, 
      "activity": 0.003
    }, 
    "enacted": {
      "bg": 131, 
      "temp": "absolute", 
      "snoozeBG": 122, 
      "recieved": true, 
      "reason": "Eventual BG 122>=120, no temp, setting 0.57U/hr", 
      "rate": 0.55, 
      "eventualBG": 122, 
      "timestamp": "2016-01-08T11:51:56.000Z", 
      "duration": 30, 
      "mealAssist": "Off: Carbs: 0 Boluses: 0 Target: 115 Deviation: 3 BGI: -1.35", 
      "tick": "+1"
    }
  }
}